Mixture_Models/__init__.py
Mixture_Models/_version.py
Mixture_Models/checkers.py
Mixture_Models/data.py
Mixture_Models/data_mnist.py
Mixture_Models/define_gradient.py
Mixture_Models/gmm.py
Mixture_Models/gmm_conc.py
Mixture_Models/mclust.py
Mixture_Models/mfa.py
Mixture_Models/mixt.py
Mixture_Models/mixture_models.py
Mixture_Models/pgmm.py
tests/__init__.py
tests/test_gmm.py
tests/test_gmm_conc.py
tests/test_mclust.py
tests/test_mfa.py
tests/test_mixt.py
tests/test_pgmm.py
tests/test_simulate_data.py
tests/utils.py
Mixture_Models-0.0.8.dist-info/LICENSE
Mixture_Models-0.0.8.dist-info/METADATA
Mixture_Models-0.0.8.dist-info/WHEEL
Mixture_Models-0.0.8.dist-info/top_level.txt
Mixture_Models-0.0.8.dist-info/RECORD
