Metadata-Version: 2.1
Name: Mixture-Models
Version: 0.0.8
Summary: A Python library for fitting mixture models using gradient based inference
Home-page: UNKNOWN
Author: Siva Rajesh Kasa
Author-email: sivarajesh.kasa@gmail.com
License: UNKNOWN
Platform: UNKNOWN
Classifier: Programming Language :: Python :: 3
Classifier: License :: OSI Approved :: MIT License
Classifier: Operating System :: OS Independent
Requires-Python: >=3.6
License-File: LICENSE
Requires-Dist: autograd (==1.3)
Requires-Dist: future (>=0.18.2)
Requires-Dist: matplotlib (>=3.5.1)
Requires-Dist: numpy (>=1.21.0)
Requires-Dist: scikit-learn (>=0.24.1)
Requires-Dist: scipy (>=1.7.0)
